ExcelDataDriver/__init__.py
ExcelDataDriver/Config/CaptureScreenShotOption.py
ExcelDataDriver/Config/DataTypes.py
ExcelDataDriver/Config/__init__.py
ExcelDataDriver/ExcelParser/ABCParserStrategy.py
ExcelDataDriver/ExcelParser/DefaultParserStrategy.py
ExcelDataDriver/ExcelParser/DefaultReferenceParserStrategy.py
ExcelDataDriver/ExcelParser/ExcelTestDataService.py
ExcelDataDriver/ExcelParser/ParserContext.py
ExcelDataDriver/ExcelParser/__init__.py
ExcelDataDriver/ExcelReferenceDataRow/ExcelReferenceDataRow.py
ExcelDataDriver/ExcelReferenceDataRow/__init__.py
ExcelDataDriver/ExcelTestDataRow/ExcelTestDataRow.py
ExcelDataDriver/ExcelTestDataRow/MandatoryTestDataColumn.py
ExcelDataDriver/ExcelTestDataRow/TestStatus.py
ExcelDataDriver/ExcelTestDataRow/__init__.py
ExcelDataDriver/Keywords/CoreExcelKeywords.py
ExcelDataDriver/Keywords/__init__.py
ExcelDataDriver/Util/CustomSelenium.py
ExcelDataDriver/Util/OpenpyxlHelper.py
ExcelDataDriver/Util/__init__.py
ExcelDataDriver/base/__init__.py
ExcelDataDriver/base/robotlibcore.py
robotframework_exceldatadriver-1.2.6.dist-info/METADATA
robotframework_exceldatadriver-1.2.6.dist-info/WHEEL
robotframework_exceldatadriver-1.2.6.dist-info/top_level.txt
robotframework_exceldatadriver-1.2.6.dist-info/RECORD
