Metadata-Version: 2.1
Name: robotframework-exceldatadriver
Version: 1.2.6
Summary: ExcelDataDriver is a Excel Data-Driven Testing library for Robot Framework.
Home-page: https://github.com/qahive/robotframework-ExcelDataDriver
Author: QA Hive Co.,Ltd
Author-email: support@qahive.com
License: Apache License 2.0
Keywords: robotframework testing automation data-driven qahive
Platform: any
Classifier: Programming Language :: Python :: 3
Classifier: Programming Language :: Python :: 3.6
Classifier: Programming Language :: Python :: 3.7
Classifier: License :: OSI Approved :: Apache Software License
Classifier: Operating System :: OS Independent
Classifier: Topic :: Software Development :: Testing
Classifier: Topic :: Software Development :: Testing :: Acceptance
Classifier: Framework :: Robot Framework
Requires-Python: >3.6
Requires-Dist: inject (==3.3.2)
Requires-Dist: openpyxl (==3.0.5)
Requires-Dist: setuptools (==41.0.1)
Requires-Dist: Pillow (>=6.2.1)
Requires-Dist: robotframework-seleniumlibrary
Requires-Dist: robotframework-puppeteerlibrary
